{
 "options": [
  [
   "brotli:shared",
   "False"
  ],
  [
   "bzip2:build_executable",
   "True"
  ],
  [
   "bzip2:shared",
   "False"
  ],
  [
   "freetype:shared",
   "False"
  ],
  [
   "freetype:with_brotli",
   "True"
  ],
  [
   "freetype:with_bzip2",
   "True"
  ],
  [
   "freetype:with_png",
   "True"
  ],
  [
   "freetype:with_zlib",
   "True"
  ],
  [
   "glfw:shared",
   "False"
  ],
  [
   "glfw:vulkan_static",
   "False"
  ],
  [
   "libpng:api_prefix",
   ""
  ],
  [
   "libpng:shared",
   "False"
  ],
  [
   "libpng:sse",
   "True"
  ],
  [
   "ogg:shared",
   "False"
  ],
  [
   "portaudio:shared",
   "False"
  ],
  [
   "small3d:shared",
   "False"
  ],
  [
   "vorbis:shared",
   "False"
  ],
  [
   "vulkan-loader:shared",
   "True"
  ],
  [
   "zlib:minizip",
   "deprecated"
  ],
  [
   "zlib:shared",
   "False"
  ]
 ],
 "root": {
  "name": null,
  "version": null,
  "user": null,
  "channel": null
 }
}